MANIFEST.in
README.md
setup.py
Partial_Include.egg-info/PKG-INFO
Partial_Include.egg-info/SOURCES.txt
Partial_Include.egg-info/dependency_links.txt
Partial_Include.egg-info/not-zip-safe
Partial_Include.egg-info/top_level.txt
partial_include/__init__.py
partial_include/models.py
partial_include.egg-info/SOURCES.txt
partial_include/templatetags/__init__.py
partial_include/templatetags/partial_include.py
tests/runtests.py
tests/tests/__init__.py
tests/tests/models.py
tests/tests/tests.py