Metadata-Version: 1.0
Name: partial-include
Version: 1.0
Summary: A more powerful include tag for Django
Home-page: https://github.com/prestontimmons/partial_include
Author: Preston Timmons
Author-email: UNKNOWN
License: UNKNOWN
Platform: UNKNOWN
